kebogyro/__init__.py
kebogyro/agent_executor.py
kebogyro/cache.py
kebogyro/config.py
kebogyro/messages.py
kebogyro/wrapper.py
kebogyro/mcp_adapter/__init__.py
kebogyro/mcp_adapter/client.py
kebogyro/mcp_adapter/prompts.py
kebogyro/mcp_adapter/resources.py
kebogyro/mcp_adapter/sessions.py
kebogyro/mcp_adapter/tools.py
kebogyro/mcp_adapter/utils.py
kebogyro-0.1.1.dist-info/METADATA
kebogyro-0.1.1.dist-info/WHEEL
kebogyro-0.1.1.dist-info/licenses/LICENSE.md
kebogyro-0.1.1.dist-info/RECORD
