Metadata-Version: 2.4
Name: kebogyro
Version: 0.1.1
Summary: An Async-first tool calling & LLM client orchestration. OpenAI-compatible, cacheable, framework-agnostic.
Author-email: Lantip <lantip@gmail.com>
License: MIT
License-File: LICENSE.md
Keywords: async,llm,mcp,openai,orchestration,tool-calling
Classifier: Development Status :: 4 - Beta
Classifier: Intended Audience :: Developers
Classifier: License :: OSI Approved :: MIT License
Classifier: Programming Language :: Python :: 3
Classifier: Programming Language :: Python :: 3.10
Requires-Python: >=3.10
Requires-Dist: aiohttp>=3.9.0
Requires-Dist: async-timeout>=4.0.3
Requires-Dist: httpx>=0.27.0
Requires-Dist: mcp>=1.4.1
Requires-Dist: openai>=1.14.0
Requires-Dist: pydantic>=2.7.0
